django_editormd-0.3.0.dist-info/DESCRIPTION.rst
django_editormd-0.3.0.dist-info/METADATA
django_editormd-0.3.0.dist-info/RECORD
django_editormd-0.3.0.dist-info/WHEEL
django_editormd-0.3.0.dist-info/metadata.json
django_editormd-0.3.0.dist-info/pbr.json
django_editormd-0.3.0.dist-info/top_level.txt
editormd/__init__.py
editormd/fields.py
editormd/forms.py
editormd/models.py
editormd/settings.py
editormd/tests.py
editormd/urls.py
editormd/views.py
editormd/widgets.py
editormd/migrations/0001_initial.py
editormd/migrations/__init__.py
editormd/static/jquery.min.js
editormd/static/editor.md/editormd.min.js
editormd/static/editor.md/css/editormd.css
editormd/static/editor.md/css/editormd.logo.css
editormd/static/editor.md/css/editormd.logo.min.css
editormd/static/editor.md/css/editormd.min.css
editormd/static/editor.md/css/editormd.preview.css
editormd/static/editor.md/css/editormd.preview.min.css
editormd/static/editor.md/fonts/FontAwesome.otf
editormd/static/editor.md/fonts/editormd-logo.eot
editormd/static/editor.md/fonts/editormd-logo.svg
editormd/static/editor.md/fonts/editormd-logo.ttf
editormd/static/editor.md/fonts/editormd-logo.woff
editormd/static/editor.md/fonts/fontawesome-webfont.eot
editormd/static/editor.md/fonts/fontawesome-webfont.svg
editormd/static/editor.md/fonts/fontawesome-webfont.ttf
editormd/static/editor.md/fonts/fontawesome-webfont.woff
editormd/static/editor.md/fonts/fontawesome-webfont.woff2
editormd/static/editor.md/images/loading.gif
editormd/static/editor.md/images/loading@2x.gif
editormd/static/editor.md/images/loading@3x.gif
editormd/static/editor.md/images/logos/editormd-favicon-16x16.ico
editormd/static/editor.md/images/logos/editormd-favicon-24x24.ico
editormd/static/editor.md/images/logos/editormd-favicon-32x32.ico
editormd/static/editor.md/images/logos/editormd-favicon-48x48.ico
editormd/static/editor.md/images/logos/editormd-favicon-64x64.ico
editormd/static/editor.md/images/logos/editormd-logo-114x114.png
editormd/static/editor.md/images/logos/editormd-logo-120x120.png
editormd/static/editor.md/images/logos/editormd-logo-144x144.png
editormd/static/editor.md/images/logos/editormd-logo-16x16.png
editormd/static/editor.md/images/logos/editormd-logo-180x180.png
