Metadata-Version: 2.0
Name: django-editormd
Version: 0.3.0
Summary: django-editormd package helps integrate editor.md with Django.
Home-page: http://github.com/chen2aaron/django-editormd
Author: xixijun
Author-email: chen2aaron@gmail.com
License: MIT
Keywords: editor.md,django,admin,editor,text,html,editor,rich,web
Platform: UNKNOWN
Classifier: Environment :: Web Environment
Classifier: Framework :: Django
Classifier: Intended Audience :: Developers
Classifier: License :: OSI Approved :: MIT License
Classifier: Operating System :: OS Independent
Classifier: Programming Language :: Python
Classifier: Programming Language :: Python :: 2.7
Classifier: Programming Language :: Python :: 3.6
Classifier: Topic :: Internet :: WWW/HTTP
Classifier: Topic :: Internet :: WWW/HTTP :: Dynamic Content
Requires-Dist: Pillow
